tsrc/__init__.py
tsrc/__main__.py
tsrc/cli/__init__.py
tsrc/cli/apply_manifest.py
tsrc/cli/env_setter.py
tsrc/cli/foreach.py
tsrc/cli/init.py
tsrc/cli/log.py
tsrc/cli/main.py
tsrc/cli/status.py
tsrc/cli/sync.py
tsrc/cloner.py
tsrc/config.py
tsrc/errors.py
tsrc/executor.py
tsrc/file_system.py
tsrc/file_system_operator.py
tsrc/git.py
tsrc/groups.py
tsrc/local_manifest.py
tsrc/manifest.py
tsrc/remote_setter.py
tsrc/repo.py
tsrc/syncer.py
tsrc/test/__init__.py
tsrc/test/cli/__init__.py
tsrc/test/cli/test_apply_manifest.py
tsrc/test/cli/test_cli.py
tsrc/test/cli/test_env_setter.py
tsrc/test/cli/test_foreach.py
tsrc/test/cli/test_init.py
tsrc/test/cli/test_log.py
tsrc/test/cli/test_main.py
tsrc/test/cli/test_shallow_clones.py
tsrc/test/cli/test_status.py
tsrc/test/cli/test_sync.py
tsrc/test/conftest.py
tsrc/test/helpers/__init__.py
tsrc/test/helpers/cli.py
tsrc/test/helpers/git_server.py
tsrc/test/helpers/test_git_server.py
tsrc/test/test_config.py
tsrc/test/test_executor.py
tsrc/test/test_file_system.py
tsrc/test/test_git_status.py
tsrc/test/test_groups.py
tsrc/test/test_manifest.py
tsrc/test/test_resolve_repos.py
tsrc/test/test_workspace_config.py
tsrc/utils.py
tsrc/workspace.py
tsrc/workspace_config.py
tsrc-3.0.1.dist-info/LICENSE
tsrc-3.0.1.dist-info/METADATA
tsrc-3.0.1.dist-info/WHEEL
tsrc-3.0.1.dist-info/entry_points.txt
tsrc-3.0.1.dist-info/RECORD
