Metadata-Version: 2.1
Name: tsrc
Version: 3.0.1
Summary: Manage groups of git repositories
Home-page: https://github.com/your-tools/tsrc
License: BSD-3-Clause
Author: Dimitri Merejkowsky
Author-email: dimitri@dmerej.info
Requires-Python: >=3.8,<4.0
Classifier: License :: OSI Approved :: BSD License
Classifier: Programming Language :: Python :: 3
Classifier: Programming Language :: Python :: 3.8
Classifier: Programming Language :: Python :: 3.9
Classifier: Programming Language :: Python :: 3.10
Classifier: Programming Language :: Python :: 3.11
Classifier: Programming Language :: Python :: 3.12
Requires-Dist: attrs (>=19.3.0,<20.0.0)
Requires-Dist: cli-ui (>=0.11.0,<0.12.0)
Requires-Dist: colored_traceback (>=0.3.0,<0.4.0)
Requires-Dist: ruamel-yaml (>=0.18.5,<0.19.0)
Requires-Dist: schema (>=0.7.1,<0.8.0)
Requires-Dist: tabulate (>=0.8.6,<0.9.0)
Requires-Dist: unidecode (>=1.1.1,<2.0.0)
Project-URL: Changelog, https://your-tools.github.io/tsrc/changelog/
Project-URL: Documentation, https://your-tools.github.io/tsrc
Project-URL: Issues, https://github.com/your-tools/tsrc/issues
Project-URL: Repository, https://github.com/your-tools/tsrc
